fastapi_keystone/__init__.py
fastapi_keystone/common/__init__.py
fastapi_keystone/common/dicts.py
fastapi_keystone/common/singleton.py
fastapi_keystone/config/__init__.py
fastapi_keystone/config/config.py
fastapi_keystone/core/__init__.py
fastapi_keystone/core/app.py
fastapi_keystone/core/contracts.py
fastapi_keystone/core/db.py
fastapi_keystone/core/exceptions.py
fastapi_keystone/core/logger.py
fastapi_keystone/core/middlewares.py
fastapi_keystone/core/pagination.py
fastapi_keystone/core/request.py
fastapi_keystone/core/response.py
fastapi_keystone/core/routing.py
fastapi_keystone/core/server.py
fastapi_keystone-0.0.14.dist-info/licenses/LICENSE
fastapi_keystone-0.0.14.dist-info/METADATA
fastapi_keystone-0.0.14.dist-info/WHEEL
fastapi_keystone-0.0.14.dist-info/top_level.txt
fastapi_keystone-0.0.14.dist-info/RECORD
