Metadata-Version: 2.4
Name: fastapi-keystone
Version: 0.0.14
Summary: 🚀 基于 FastAPI 的现代化快速开发框架，提供企业级的多租户、依赖注入、路由管理等特性
Author-email: alpha <alphaqiu@gmail.com>
License-Expression: MIT
Project-URL: Homepage, https://github.com/alphaqiu/fastapi-keystone
Project-URL: Documentation, https://github.com/alphaqiu/fastapi-keystone#readme
Project-URL: Repository, https://github.com/alphaqiu/fastapi-keystone
Project-URL: Issues, https://github.com/alphaqiu/fastapi-keystone/issues
Project-URL: Changelog, https://github.com/alphaqiu/fastapi-keystone/releases
Keywords: fastapi,framework,mvc,async,orm
Classifier: Development Status :: 4 - Beta
Classifier: Intended Audience :: Developers
Classifier: Operating System :: OS Independent
Classifier: Programming Language :: Python :: 3
Classifier: Programming Language :: Python :: 3.10
Classifier: Programming Language :: Python :: 3.11
Classifier: Programming Language :: Python :: 3.12
Classifier: Programming Language :: Python :: 3.13
Classifier: Framework :: FastAPI
Classifier: Topic :: Internet :: WWW/HTTP :: HTTP Servers
Classifier: Topic :: Software Development :: Libraries :: Python Modules
Requires-Python: >=3.10
License-File: LICENSE
Requires-Dist: aiomysql>=0.2.0
Requires-Dist: aiosqlite>=0.21.0
Requires-Dist: asyncio>=3.4.3
Requires-Dist: asyncpg>=0.30.0
Requires-Dist: cachetools<7.0.0,>=6.0.0
Requires-Dist: fastapi>=0.115.12
Requires-Dist: injector>=0.22.0
Requires-Dist: pydantic<3.0.0,>=2.11.5
Requires-Dist: pydantic-settings>=2.9.1
Requires-Dist: python-ulid>=3.0.0
Requires-Dist: pyyaml>=6.0.2
Requires-Dist: redis<7.0.0,>=6.2.0
Requires-Dist: rich>=14.0.0
Requires-Dist: sqlalchemy>=2.0.41
Dynamic: license-file
